pyautoscreenshot/__init__.py
pyautoscreenshot/__main__.py
pyautoscreenshot/main.py
pyautoscreenshot-0.1.1.dist-info/METADATA
pyautoscreenshot-0.1.1.dist-info/WHEEL
pyautoscreenshot-0.1.1.dist-info/entry_points.txt
pyautoscreenshot-0.1.1.dist-info/top_level.txt
pyautoscreenshot-0.1.1.dist-info/RECORD
