Metadata-Version: 2.4
Name: pyautoscreenshot
Version: 0.1.1
Summary: Fast save screenshots every x seconds for workspace
Project-URL: Homepage, https://github.com/fxyzbtc/pyautoscreenshot
Project-URL: Issues, https://github.com/fxyzbtc/pyautoscreenshot/issues
Requires-Python: >=3.12
Requires-Dist: loguru>=0.7.3
Requires-Dist: pillow>=11.1.0
Requires-Dist: pyautogui>=0.9.54
Requires-Dist: typer>=0.15.2
Provides-Extra: dev
Requires-Dist: pytest>=8.3.5; extra == "dev"
Requires-Dist: pytest-cov>=4.1.0; extra == "dev"
Requires-Dist: black>=24.2.0; extra == "dev"
Requires-Dist: isort>=5.13.2; extra == "dev"
